sc2common/__init__.py
sc2common/__version__.py
sc2common/commonUtilFuncs.py
sc2common/constants.py
sc2common/constants_shapes.py
sc2common/containers.py
sc2common/types.py
sc2common/variables.py
sc2common-1.1.2.dist-info/METADATA
sc2common-1.1.2.dist-info/RECORD
sc2common-1.1.2.dist-info/WHEEL
sc2common-1.1.2.dist-info/entry_points.txt
sc2common-1.1.2.dist-info/top_level.txt
