Metadata-Version: 2.1
Name: sc2common
Version: 1.1.2
Summary: Basic definitions for various SC2 game components.
Home-page: https://github.com/ttinies/sc2common
Author: Versentiedge LLC
Author-email: help.fool@versentiedge.com
License: Apache License 2.0
Platform: UNKNOWN
Classifier: License :: OSI Approved :: Apache Software License
Classifier: Programming Language :: Python
Classifier: Programming Language :: Python :: 3
Classifier: Programming Language :: Python :: 3.6
Classifier: Programming Language :: Python :: Implementation :: CPython
Classifier: Programming Language :: Python :: Implementation :: PyPy
Classifier: Topic :: Games/Entertainment :: Real Time Strategy
Classifier: Topic :: Scientific/Engineering :: Artificial Intelligence
Requires-Python: >3.4
Requires-Dist: s2clientprotocol
